bottilities/__init__.py
bottilities/drewtilities.py
bottilities-1.3.3.dist-info/LICENSE
bottilities-1.3.3.dist-info/METADATA
bottilities-1.3.3.dist-info/WHEEL
bottilities-1.3.3.dist-info/entry_points.txt
bottilities-1.3.3.dist-info/top_level.txt
bottilities-1.3.3.dist-info/RECORD
