Metadata-Version: 2.1
Name: bottilities
Version: 1.3.3
Summary: Simple utilities for dev work.
Home-page: https://github.com/lunemercove/bottilities
Download-URL: https://github.com/lunemercove/bottilities/archive/v1.3.3.tar.gz
Author: Luné Mercové
Author-email: pypi@lune.gay
License: BSD3
Classifier: Development Status :: 5 - Production/Stable
Classifier: Environment :: Console
Classifier: Intended Audience :: Developers
Classifier: License :: OSI Approved :: BSD License
Classifier: Natural Language :: English
Classifier: Operating System :: MacOS :: MacOS X
Classifier: Operating System :: POSIX
Classifier: Operating System :: POSIX :: BSD
Classifier: Operating System :: POSIX :: Linux
Classifier: Operating System :: Microsoft :: Windows
Classifier: Programming Language :: Python :: 3.6
Classifier: Programming Language :: Python :: 3.7
Classifier: Programming Language :: Python :: 3.8
Classifier: Programming Language :: Python :: 3.9
Classifier: Programming Language :: Python :: 3.10
Classifier: Programming Language :: Python :: 3 :: Only
Classifier: Programming Language :: Python :: Implementation :: CPython
Classifier: Topic :: Software Development :: Libraries
Classifier: Typing :: Typed
Requires-Python: >=3.6
License-File: LICENSE
Requires-Dist: clint (<0.6.0,>=0.5.1)
Requires-Dist: requests (<3.0.0,>=2.21.0)
